statswag/__init__.py
statswag/setup.py
statswag/datasets/__init__.py
statswag/datasets/labels_generator.py
statswag/estimators/MLE.py
statswag/estimators/__init__.py
statswag/estimators/agreement.py
statswag/estimators/base.py
statswag/estimators/iwmv.py
statswag/estimators/majorityvote.py
statswag/estimators/spectral.py
statswag/estimators/tests/__init__.py
statswag/estimators/tests/test_estimators.py
statswag/estimators/tests/test_estimators_nan.py
statswag/estimators/tests/test_estimators_str.py
statswag/estimators/tests/test_estimators_str_nan.py
statswag/examples/__init__.py
statswag/metrics/__init__.py
statswag/tests/__init__.py
statswag/utils/__init__.py
statswag-1.0.dist-info/METADATA
statswag-1.0.dist-info/WHEEL
statswag-1.0.dist-info/top_level.txt
statswag-1.0.dist-info/RECORD
