Metadata-Version: 2.1
Name: statswag
Version: 1.0
Summary: Statistics Without Affirmed Ground Truth
Home-page: http://github.com/mitll/statswag
Author: MIT LL
Author-email: UNKNOWN
License:       DISTRIBUTION STATEMENT A. Approved for public release. Distribution is unlimited.
